datasette_configure_asgi.py
datasette_configure_asgi-0.1.dist-info/LICENSE
datasette_configure_asgi-0.1.dist-info/METADATA
datasette_configure_asgi-0.1.dist-info/WHEEL
datasette_configure_asgi-0.1.dist-info/entry_points.txt
datasette_configure_asgi-0.1.dist-info/top_level.txt
datasette_configure_asgi-0.1.dist-info/RECORD
