Metadata-Version: 2.1
Name: datasette-configure-asgi
Version: 0.1
Summary: Datasette plugin for configuring arbitrary ASGI middleware
Home-page: https://github.com/simonw/datasette-configure-asgi
Author: Simon Willison
License: Apache License, Version 2.0
Platform: UNKNOWN
Provides-Extra: test
Requires-Dist: pytest ; extra == 'test'
Requires-Dist: pytest-asyncio ; extra == 'test'
Requires-Dist: asgiref (==3.1.2) ; extra == 'test'
Requires-Dist: datasette ; extra == 'test'
